connectsensor/__init__.py
connectsensor/_kingspan_export.py
connectsensor/_kingspan_notifier.py
connectsensor/_kingspan_status.py
connectsensor/client.py
connectsensor/client.pyi
connectsensor/debug.py
connectsensor/debug.pyi
connectsensor/exceptions.py
connectsensor/exceptions.pyi
connectsensor/tank.py
connectsensor/tank.pyi
kingspan_connect_sensor-3.2.0.dist-info/licenses/LICENSE
mitm/parse_headers.py
kingspan_connect_sensor-3.2.0.dist-info/METADATA
kingspan_connect_sensor-3.2.0.dist-info/WHEEL
kingspan_connect_sensor-3.2.0.dist-info/entry_points.txt
kingspan_connect_sensor-3.2.0.dist-info/top_level.txt
kingspan_connect_sensor-3.2.0.dist-info/RECORD
