Metadata-Version: 2.4
Name: kingspan-connect-sensor
Version: 3.2.0
Summary: API to get oil tank from Kingspan SENSiT sensors
Author-email: Jon Connell <python@figsandfudge.com>
License-Expression: MIT
Project-URL: Documentation, https://github.com/masaccio/kingspan-connect-sensor/blob/main/README.md
Project-URL: Repository, https://github.com/masaccio/kingspan-connect-sensor
Classifier: Development Status :: 5 - Production/Stable
Classifier: Intended Audience :: Developers
Classifier: Intended Audience :: System Administrators
Classifier: Programming Language :: Python
Classifier: Programming Language :: Python :: 3
Requires-Python: <4.0,>=3.10
License-File: LICENSE
Requires-Dist: async-property<0.3.0,>=0.2.1
Requires-Dist: asyncio<4.0.0,>=3.4.3
Requires-Dist: datetime<5.0.0,>=4.7
Requires-Dist: httpx>=0.28
Requires-Dist: requests<3.0.0,>=2.28.1
Requires-Dist: lxml>=5.3
Requires-Dist: zeep<5.0.0,>=4.2.0
Requires-Dist: xlsxwriter>=3.2.4
Dynamic: license-file
